LICENSE.txt
README.md
setup.cfg
setup.py
ocotillo/__init__.py
ocotillo/api.py
ocotillo/dataset.py
ocotillo/model_loader.py
ocotillo/transcribe.py
ocotillo/utils.py
ocotillo.egg-info/PKG-INFO
ocotillo.egg-info/SOURCES.txt
ocotillo.egg-info/dependency_links.txt
ocotillo.egg-info/requires.txt
ocotillo.egg-info/top_level.txt