Metadata-Version: 2.1
Name: ocotillo
Version: 1.0.5
Summary: A simple & fast speech transcription toolkit
Home-page: https://github.com/neonbjb/ocotillo
Author: James
Author-email: james@adamant.ai
License: UNKNOWN
Download-URL: https://github.com/neonbjb/ocotillo/archive/refs/tags/1.0.2.tar.gz
Platform: UNKNOWN
Classifier: Programming Language :: Python :: 3
Classifier: License :: OSI Approved :: Apache Software License
Classifier: Operating System :: OS Independent
Requires-Python: >=3.6
License-File: LICENSE.txt
